{"wifi": [{"nodeId": "1", "y": "2599", "nodeName": "arc-0201-a", "macAddr": "e8:ba:70:61:c9:60", "x": "569"}, {"nodeId": "2", "y": "2599", "nodeName": "arc-0202-a", "macAddr": "e8:ba:70:61:af:20", "x": "2274"}, {"nodeId": "3", "y": "731", "nodeName": "arc-0204-a", "macAddr": "04:da:d2:74:cf:30", "x": "2964"}, {"nodeId": "4", "y": "934", "nodeName": "arc-0205-a", "macAddr": "e8:ba:70:52:3b:e0", "x": "5400"}, {"nodeId": "5", "y": "609", "nodeName": "arc-0205-b", "macAddr": "e8:ba:70:52:bf:80", "x": "4060"}, {"nodeId": "6", "y": "2315", "nodeName": "arc-0206-a", "macAddr": "e8:ba:70:52:0b:40", "x": "4263"}, {"nodeId": "7", "y": "2924", "nodeName": "arc-0206-b", "macAddr": "e8:ba:70:52:1e:90", "x": "6578"}, {"nodeId": "8", "y": "2842", "nodeName": "arc-0212-a", "macAddr": "e8:ba:70:52:ab:e0", "x": "8445"}, {"nodeId": "9", "y": "2964", "nodeName": "arc-0210-a", "macAddr": "e8:ba:70:61:b3:50", "x": "10435"}, {"nodeId": "10", "y": "1706", "nodeName": "arc-0212-b", "macAddr": "50:06:04:8d:d0:10", "x": "7796"}, {"nodeId": "11", "y": "1868", "nodeName": "arc-0213-a", "macAddr": "04:da:d2:74:c8:70", "x": "8608"}, {"nodeId": "12", "y": "1097", "nodeName": "arc-0214-a", "macAddr": "e8:ba:70:52:bd:80", "x": "10800"}, {"nodeId": "13", "y": "731", "nodeName": "arc-0239-a", "macAddr": "e8:ba:70:61:a8:80", "x": "9866"}, {"nodeId": "14", "y": "934", "nodeName": "arc-0241-a", "macAddr": "28:93:fe:d3:8b:20", "x": "6902"}], "info": {"northAt": "315"}, "map": [{"nodeId": "1", "linkTo": "2 ", "y": "2436", "nodeName": "TO LT15", "x": "0"}, {"nodeId": "2", "linkTo": "1, 3, 4  ", "y": "2436", "nodeName": "P2", "x": "2152"}, {"nodeId": "3", "linkTo": "2", "y": "731", "nodeName": "Linkway", "x": "2152"}, {"nodeId": "4", "linkTo": "2, 5, 6, 7", "y": "2436", "nodeName": "P4", "x": "2883"}, {"nodeId": "5", "linkTo": "4, 8 ", "y": "1787", "nodeName": "P5", "x": "2883"}, {"nodeId": "6", "linkTo": "4", "y": "2924", "nodeName": "Seminar Room 6", "x": "2883"}, {"nodeId": "7", "linkTo": "4, 10", "y": "2436", "nodeName": "Lobby ", "x": "3776"}, {"nodeId": "8", "linkTo": "5, 9, 10 ", "y": "1787", "nodeName": "P8", "x": "3330"}, {"nodeId": "9", "linkTo": "8", "y": "934", "nodeName": "Seminar Room 2", "x": "3330"}, {"nodeId": "10", "linkTo": "7, 8, 11", "y": "1787", "nodeName": "P10", "x": "3776"}, {"nodeId": "11", "linkTo": "10, 12, 13, 14", "y": "1787", "nodeName": "Student Area", "x": "5603"}, {"nodeId": "12", "linkTo": "11", "y": "2924", "nodeName": "Seminar Room 1", "x": "5603"}, {"nodeId": "13", "linkTo": "11, 36", "y": "609", "nodeName": "P13", "x": "5603"}, {"nodeId": "14", "linkTo": "11, 15, 37 ", "y": "1787", "nodeName": "P14", "x": "7065"}, {"nodeId": "15", "linkTo": "14, 32 ", "y": "2802", "nodeName": "P15", "x": "7065"}, {"nodeId": "16", "linkTo": "18, 37", "y": "731", "nodeName": "P16", "x": "7065"}, {"nodeId": "17", "linkTo": "39, 19, 21 ", "y": "2802", "nodeName": "P17", "x": "9014"}, {"nodeId": "18", "linkTo": "16, 20, 22", "y": "731", "nodeName": "P18", "x": "8283"}, {"nodeId": "19", "linkTo": "17", "y": "2193", "nodeName": "Executive Classroom", "x": "9014"}, {"nodeId": "20", "linkTo": "18", "y": "1056", "nodeName": "Tutorial Room 11", "x": "8283"}, {"nodeId": "21", "linkTo": "17, 23, 24 ", "y": "2802", "nodeName": "P21", "x": "9460"}, {"nodeId": "22", "linkTo": "18, 25, 34", "y": "731", "nodeName": "P22", "x": "9744"}, {"nodeId": "23", "linkTo": "21", "y": "3248", "nodeName": "Seminar Room 9", "x": "9460"}, {"nodeId": "24", "linkTo": "21, 27, 28", "y": "2802", "nodeName": "P24", "x": "11003"}, {"nodeId": "25", "linkTo": "22", "y": "1056", "nodeName": "NUS Hacker's Room", "x": "9744"}, {"nodeId": "26", "linkTo": "34, 28, 29 ", "y": "691", "nodeName": "P26", "x": "11003"}, {"nodeId": "27", "linkTo": "24 ", "y": "3248", "nodeName": "Seminar Room 11", "x": "11003"}, {"nodeId": "28", "linkTo": "24, 26, 30", "y": "1259", "nodeName": "P28", "x": "11003"}, {"nodeId": "29", "linkTo": "26, 31 ", "y": "691", "nodeName": "P29", "x": "11571"}, {"nodeId": "30", "linkTo": "28  ", "y": "731", "nodeName": "TO Canteen", "x": "12180"}, {"nodeId": "31", "linkTo": "29 ", "y": "406", "nodeName": "TO 2-2-1", "x": "11815"}, {"nodeId": "32", "linkTo": "15, 33, 39 ", "y": "2802", "nodeName": "P32", "x": "7552"}, {"nodeId": "33", "linkTo": "32", "y": "3086", "nodeName": "Seminar Room 7", "x": "7552"}, {"nodeId": "34", "linkTo": "22, 26, 35 ", "y": "731", "nodeName": "P34", "x": "10272"}, {"nodeId": "35", "linkTo": "34 ", "y": "447", "nodeName": "Tutorial Room 5", "x": "10272"}, {"nodeId": "36", "linkTo": "13", "y": "609", "nodeName": "Cerebro", "x": "4263"}, {"nodeId": "37", "linkTo": "14, 16, 38 ", "y": "1543", "nodeName": "P37", "x": "7065"}, {"nodeId": "38", "linkTo": "37", "y": "1543", "nodeName": "SR3 Front", "x": "7552"}, {"nodeId": "39", "linkTo": "17, 32, 40 ", "y": "2802", "nodeName": "P39", "x": "8811"}, {"nodeId": "40", "linkTo": "39", "y": "2436", "nodeName": "SR3 Back", "x": "8811"}]}